{
  "schema_version": "runtime-tools.plan.v0.1",
  "plan_id": "runtime-closure.v4",
  "registry_id": "runtime-closure",
  "world_id": "sonoma-14.4.1-23E224-arm64-dyld-2c0602c5",
  "profiles": [
    "runtime-closure:file:v2_alias_literals",
    "runtime-closure:file:v2_private_literals",
    "runtime-closure:file:v2_data_literals",
    "runtime-closure:mach:v1_service_discriminator",
    "runtime-closure:iokit:v5_service_only",
    "runtime-closure:iokit:v6_user_client_only",
    "runtime-closure:iokit:v7_service_user_client_both",
    "runtime-closure:iokit:v8_external_method"
  ],
  "lanes": {
    "baseline": true,
    "scenario": true,
    "oracle": true
  },
  "controls": {
    "baseline": true
  },
  "apply_preflight_profile": "book/experiments/hardened-runtime/sb/apply_preflight_allow.sb",
  "notes": "Runtime closure lanes for canonicalization, mach, and IOSurface user-client probes to support probe-op-structure."
}
