{
  "data": {
    "correlation_id": null,
    "deny_lines": [
      "2025-12-31 15:15:56.661599-0800  localhost kernel[0]: (Sandbox) Sandbox: ProbeService_minimal(52081) deny(1) file-read-data /Users/achyland/Documents"
    ],
    "duration_ms": null,
    "end": null,
    "last": "30s",
    "layer_attribution": {
      "seatbelt": "observer_only"
    },
    "log_error": null,
    "log_rc": 0,
    "log_stderr": "",
    "log_stdout": "Timestamp                       (process)[PID]    \n2025-12-31 15:15:56.661599-0800  localhost kernel[0]: (Sandbox) Sandbox: ProbeService_minimal(52081) deny(1) file-read-data /Users/achyland/Documents\n2025-12-31 15:15:56.678070-0800  localhost log[52083]: [com.apple.log:] log run noninteractively, parent: 52082 (sandbox-log-observer), args: '/usr/bin/log' 'show' '--style' 'syslog' '--info' '--debug' '--last' '30s' '--predicate' '((eventMessage CONTAINS[c] \"Sandbox: ProbeService_minimal(52081)\") OR ((eventMessage CONTAINS[c",
    "log_truncated": false,
    "mode": "show",
    "observed_deny": true,
    "observed_lines": 3,
    "observer_schema_version": 1,
    "pid": 52081,
    "plan_id": "policywitness-deny-atlas:smoke:smoke-fb05c455-f75e-4ab3-b091-c726db1353e3",
    "predicate": "((eventMessage CONTAINS[c] \"Sandbox: ProbeService_minimal(52081)\") OR ((eventMessage CONTAINS[c] \"deny\") AND (eventMessage CONTAINS[c] \"52081\")))",
    "process_name": "ProbeService_minimal",
    "row_id": "minimal.fs_op_listdir_home_documents",
    "start": null,
    "stop_on_pid_exit": false
  },
  "generated_at_unix_ms": 1767222957004,
  "kind": "sandbox_log_observer_report",
  "result": {
    "errno": null,
    "error": null,
    "exit_code": 0,
    "normalized_outcome": null,
    "ok": true,
    "rc": null,
    "stderr": null,
    "stdout": null
  },
  "schema_version": 1
}
