{
  "world_id": "sonoma-14.4.1-23E224-arm64-dyld-2c0602c5",
  "profiles": {
    "probe-op-structure:file:v1_file_require_any": {
      "blob": "book/experiments/field2-final-final/probe-op-structure/sb/v1_file_require_any.sb",
      "mode": "sbpl",
      "family": "file-read",
      "semantic_group": "file-read:anchor-check",
      "probes": [
        {
          "name": "tmp_foo",
          "operation": "file-read*",
          "target": "/tmp/foo",
          "expected": "allow",
          "expectation_id": "probe-op-structure:file:v1_file_require_any:tmp_foo"
        },
        {
          "name": "etc_hosts",
          "operation": "file-read*",
          "target": "/etc/hosts",
          "expected": "allow",
          "expectation_id": "probe-op-structure:file:v1_file_require_any:etc_hosts"
        }
      ]
    },
    "probe-op-structure:mach:v3_mach_global_local": {
      "blob": "book/experiments/field2-final-final/probe-op-structure/sb/v3_mach_global_local.sb",
      "mode": "sbpl",
      "family": "mach-lookup",
      "semantic_group": "mach:anchor-check",
      "probes": [
        {
          "name": "cfprefsd_agent",
          "operation": "mach-lookup",
          "target": "com.apple.cfprefsd.agent",
          "expected": "allow",
          "expectation_id": "probe-op-structure:mach:v3_mach_global_local:cfprefsd_agent",
          "driver": "sandbox_mach_probe"
        }
      ]
    },
    "probe-op-structure:iokit:v5_iokit_class_property": {
      "blob": "book/experiments/field2-final-final/probe-op-structure/sb/v5_iokit_class_property.sb",
      "mode": "sbpl",
      "family": "iokit-open-service",
      "semantic_group": "iokit:anchor-check",
      "probes": [
        {
          "name": "iousb_host_interface",
          "operation": "iokit-open-service",
          "target": "IOUSBHostInterface",
          "expected": "allow",
          "expectation_id": "probe-op-structure:iokit:v5_iokit_class_property:iousb_host_interface",
          "driver": "sandbox_iokit_probe"
        }
      ]
    }
  }
}