{
  "world_id": "sonoma-14.4.1-23E224-arm64-dyld-2c0602c5",
  "entrypoint": "book/tools/entitlement/EntitlementJail.app/Contents/MacOS/entitlement-jail",
  "kind": "inventory",
  "commands": [
    {
      "command": [
        "book/tools/entitlement/EntitlementJail.app/Contents/MacOS/entitlement-jail",
        "health-check"
      ],
      "exit_code": 0,
      "stdout": "{\n  \"data\": {\n    \"ok\": true,\n    \"profiles\": [\n      {\n        \"bundle_id\": \"com.yourteam.entitlement-jail.ProbeService_bookmarks_app_scope\",\n        \"kind\": \"probe\",\n        \"ok\": true,\n        \"probes\": [\n          {\n            \"error\": null,\n            \"exit_code\": 0,\n            \"normalized_outcome\": \"ok\",\n            \"parse_error\": null,\n            \"probe_id\": \"capabilities_snapshot\",\n            \"rc\": 0,\n            \"stderr\": null\n          },\n          {\n            \"error\": null,\n            \"exit_code\": 0,\n            \"normalized_outcome\": \"ok\",\n            \"parse_error\": null,\n            \"probe_id\": \"world_shape\",\n            \"rc\": 0,\n            \"stderr\": null\n          },\n          {\n            \"error\": null,\n            \"exit_code\": 0,\n            \"normalized_outcome\": \"ok\",\n            \"parse_error\": null,\n            \"probe_id\": \"fs_op\",\n            \"rc\": 0,\n            \"stderr\": null\n          }\n        ],\n        \"profile_id\": \"bookmarks_app_scope\"\n      },\n      {\n        \"bundle_id\": \"com.yourteam.entitlement-jail.ProbeService_debuggable\",\n        \"kind\": \"probe\",\n        \"ok\": true,\n        \"probes\": [\n          {\n            \"error\": null,\n            \"exit_code\": 0,\n            \"normalized_outcome\": \"ok\",\n            \"parse_error\": null,\n            \"probe_id\": \"capabilities_snapshot\",\n            \"rc\": 0,\n            \"stderr\": null\n          },\n          {\n            \"error\": null,\n            \"exit_code\": 0,\n            \"normalized_outcome\": \"ok\",\n            \"parse_error\": null,\n            \"probe_id\": \"world_shape\",\n            \"rc\": 0,\n            \"stderr\": null\n          },\n          {\n            \"error\": null,\n            \"exit_code\": 0,\n            \"normalized_outcome\": \"ok\",\n            \"parse_error\": null,\n            \"probe_id\": \"fs_op\",\n            \"rc\": 0,\n            \"stderr\": null\n          }\n        ],\n        \"profile_id\": \"debuggable\"\n      },\n      {\n        \"bundle_id\": \"com.yourteam.entitlement-jail.ProbeService_downloads_rw\",\n        \"kind\": \"probe\",\n        \"ok\": true,\n        \"probes\": [\n          {\n            \"error\": null,\n            \"exit_code\": 0,\n            \"normalized_outcome\": \"ok\",\n            \"parse_error\": null,\n            \"probe_id\": \"capabilities_snapshot\",\n            \"rc\": 0,\n            \"stderr\": null\n          },\n          {\n            \"error\": null,\n            \"exit_code\": 0,\n            \"normalized_outcome\": \"ok\",\n            \"parse_error\": null,\n            \"probe_id\": \"world_shape\",\n            \"rc\": 0,\n            \"stderr\": null\n          },\n          {\n            \"error\": null,\n            \"exit_code\": 0,\n            \"normalized_outcome\": \"ok\",\n            \"parse_error\": null,\n            \"probe_id\": \"fs_op\",\n            \"rc\": 0,\n            \"stderr\": null\n          }\n        ],\n        \"profile_id\": \"downloads_rw\"\n      },\n      {\n        \"bundle_id\": \"com.yourteam.entitlement-jail.ProbeService_dyld_env_enabled\",\n        \"kind\": \"probe\",\n        \"ok\": true,\n        \"probes\": [\n          {\n            \"error\": null,\n            \"exit_code\": 0,\n            \"normalized_outcome\": \"ok\",\n            \"parse_error\": null,\n            \"probe_id\": \"capabilities_snapshot\",\n            \"rc\": 0,\n            \"stderr\": null\n          },\n          {\n            \"error\": null,\n            \"exit_code\": 0,\n            \"normalized_outcome\": \"ok\",\n            \"parse_error\": null,\n            \"probe_id\": \"world_shape\",\n            \"rc\": 0,\n            \"stderr\": null\n          },\n          {\n            \"error\": null,\n            \"exit_code\": 0,\n            \"normalized_outcome\": \"ok\",\n            \"parse_error\": null,\n            \"probe_id\": \"fs_op\",\n            \"rc\": 0,\n            \"stderr\": null\n          }\n        ],\n        \"profile_id\": \"dyld_env_enabled\"\n      },\n      {\n        \"bundle_id\": \"com.yourteam.entitlement-jail.ProbeService_fully_injectable\",\n        \"kind\": \"probe\",\n        \"ok\": true,\n        \"probes\": [\n          {\n            \"error\": null,\n            \"exit_code\": 0,\n            \"normalized_outcome\": \"ok\",\n            \"parse_error\": null,\n            \"probe_id\": \"capabilities_snapshot\",\n            \"rc\": 0,\n            \"stderr\": null\n          },\n          {\n            \"error\": null,\n            \"exit_code\": 0,\n            \"normalized_outcome\": \"ok\",\n            \"parse_error\": null,\n            \"probe_id\": \"world_shape\",\n            \"rc\": 0,\n            \"stderr\": null\n          },\n          {\n            \"error\": null,\n            \"exit_code\": 0,\n            \"normalized_outcome\": \"ok\",\n            \"parse_error\": null,\n            \"probe_id\": \"fs_op\",\n            \"rc\": 0,\n            \"stderr\": null\n          }\n        ],\n        \"profile_id\": \"fully_injectable\"\n      },\n      {\n        \"bundle_id\": \"com.yourteam.entitlement-jail.ProbeService_jit_map_jit\",\n        \"kind\": \"probe\",\n        \"ok\": true,\n        \"probes\": [\n          {\n            \"error\": null,\n            \"exit_code\": 0,\n            \"normalized_outcome\": \"ok\",\n            \"parse_error\": null,\n            \"probe_id\": \"capabilities_snapshot\",\n            \"rc\": 0,\n            \"stderr\": null\n          },\n          {\n            \"error\": null,\n            \"exit_code\": 0,\n            \"normalized_outcome\": \"ok\",\n            \"parse_error\": null,\n            \"probe_id\": \"world_shape\",\n            \"rc\": 0,\n            \"stderr\": null\n          },\n          {\n            \"error\": null,\n            \"exit_code\": 0,\n            \"normalized_outcome\": \"ok\",\n            \"parse_error\": null,\n            \"probe_id\": \"fs_op\",\n            \"rc\": 0,\n            \"stderr\": null\n          }\n        ],\n        \"profile_id\": \"jit_map_jit\"\n      },\n      {\n        \"bundle_id\": \"com.yourteam.entitlement-jail.ProbeService_jit_rwx_legacy\",\n        \"kind\": \"probe\",\n        \"ok\": true,\n        \"probes\": [\n          {\n            \"error\": null,\n            \"exit_code\": 0,\n            \"normalized_outcome\": \"ok\",\n            \"parse_error\": null,\n            \"probe_id\": \"capabilities_snapshot\",\n            \"rc\": 0,\n            \"stderr\": null\n          },\n          {\n            \"error\": null,\n            \"exit_code\": 0,\n            \"normalized_outcome\": \"ok\",\n            \"parse_error\": null,\n            \"probe_id\": \"world_shape\",\n            \"rc\": 0,\n            \"stderr\": null\n          },\n          {\n            \"error\": null,\n            \"exit_code\": 0,\n            \"normalized_outcome\": \"ok\",\n            \"parse_error\": null,\n            \"probe_id\": \"fs_op\",\n            \"rc\": 0,\n            \"stderr\": null\n          }\n        ],\n        \"profile_id\": \"jit_rwx_legacy\"\n      },\n      {\n        \"bundle_id\": \"com.yourteam.entitlement-jail.ProbeService_minimal\",\n        \"kind\": \"probe\",\n        \"ok\": true,\n        \"probes\": [\n          {\n            \"error\": null,\n            \"exit_code\": 0,\n            \"normalized_outcome\": \"ok\",\n            \"parse_error\": null,\n            \"probe_id\": \"capabilities_snapshot\",\n            \"rc\": 0,\n            \"stderr\": null\n          },\n          {\n            \"error\": null,\n            \"exit_code\": 0,\n            \"normalized_outcome\": \"ok\",\n            \"parse_error\": null,\n            \"probe_id\": \"world_shape\",\n            \"rc\": 0,\n            \"stderr\": null\n          },\n          {\n            \"error\": null,\n            \"exit_code\": 0,\n            \"normalized_outcome\": \"ok\",\n            \"parse_error\": null,\n            \"probe_id\": \"fs_op\",\n            \"rc\": 0,\n            \"stderr\": null\n          }\n        ],\n        \"profile_id\": \"minimal\"\n      },\n      {\n        \"bundle_id\": \"com.yourteam.entitlement-jail.ProbeService_net_client\",\n        \"kind\": \"probe\",\n        \"ok\": true,\n        \"probes\": [\n          {\n            \"error\": null,\n            \"exit_code\": 0,\n            \"normalized_outcome\": \"ok\",\n            \"parse_error\": null,\n            \"probe_id\": \"capabilities_snapshot\",\n            \"rc\": 0,\n            \"stderr\": null\n          },\n          {\n            \"error\": null,\n            \"exit_code\": 0,\n            \"normalized_outcome\": \"ok\",\n            \"parse_error\": null,\n            \"probe_id\": \"world_shape\",\n            \"rc\": 0,\n            \"stderr\": null\n          },\n          {\n            \"error\": null,\n            \"exit_code\": 0,\n            \"normalized_outcome\": \"ok\",\n            \"parse_error\": null,\n            \"probe_id\": \"fs_op\",\n            \"rc\": 0,\n            \"stderr\": null\n          }\n        ],\n        \"profile_id\": \"net_client\"\n      },\n      {\n        \"bundle_id\": \"com.yourteam.entitlement-jail.ProbeService_plugin_host_relaxed\",\n        \"kind\": \"probe\",\n        \"ok\": true,\n        \"probes\": [\n          {\n            \"error\": null,\n            \"exit_code\": 0,\n            \"normalized_outcome\": \"ok\",\n            \"parse_error\": null,\n            \"probe_id\": \"capabilities_snapshot\",\n            \"rc\": 0,\n            \"stderr\": null\n          },\n          {\n            \"error\": null,\n            \"exit_code\": 0,\n            \"normalized_outcome\": \"ok\",\n            \"parse_error\": null,\n            \"probe_id\": \"world_shape\",\n            \"rc\": 0,\n            \"stderr\": null\n          },\n          {\n            \"error\": null,\n            \"exit_code\": 0,\n            \"normalized_outcome\": \"ok\",\n            \"parse_error\": null,\n            \"probe_id\": \"fs_op\",\n            \"rc\": 0,\n            \"stderr\": null\n          }\n        ],\n        \"profile_id\": \"plugin_host_relaxed\"\n      },\n      {\n        \"bundle_id\": \"com.yourteam.entitlement-jail.ProbeService_user_selected_executable\",\n        \"kind\": \"probe\",\n        \"ok\": true,\n        \"probes\": [\n          {\n            \"error\": null,\n            \"exit_code\": 0,\n            \"normalized_outcome\": \"ok\",\n            \"parse_error\": null,\n            \"probe_id\": \"capabilities_snapshot\",\n            \"rc\": 0,\n            \"stderr\": null\n          },\n          {\n            \"error\": null,\n            \"exit_code\": 0,\n            \"normalized_outcome\": \"ok\",\n            \"parse_error\": null,\n            \"probe_id\": \"world_shape\",\n            \"rc\": 0,\n            \"stderr\": null\n          },\n          {\n            \"error\": null,\n            \"exit_code\": 0,\n            \"normalized_outcome\": \"ok\",\n            \"parse_error\": null,\n            \"probe_id\": \"fs_op\",\n            \"rc\": 0,\n            \"stderr\": null\n          }\n        ],\n        \"profile_id\": \"user_selected_executable\"\n      }\n    ],\n    \"profiles_path\": \"/Users/achyland/Desktop/VM-BRIDGE/SANDBOX_LORE/book/tools/entitlement/EntitlementJail.app/Contents/Resources/Evidence/profiles.json\"\n  },\n  \"generated_at_unix_ms\": 1766618482827,\n  \"kind\": \"health_check_report\",\n  \"result\": {\n    \"errno\": null,\n    \"error\": null,\n    \"exit_code\": 0,\n    \"normalized_outcome\": null,\n    \"ok\": true,\n    \"rc\": null,\n    \"stderr\": null,\n    \"stdout\": null\n  },\n  \"schema_version\": 1\n}\n",
      "stderr": ""
    },
    {
      "command": [
        "book/tools/entitlement/EntitlementJail.app/Contents/MacOS/entitlement-jail",
        "list-profiles"
      ],
      "exit_code": 0,
      "stdout": "{\n  \"data\": {\n    \"generated_at\": \"2025-12-24T23:06:51Z\",\n    \"profiles\": [\n      {\n        \"bundle_id\": \"com.yourteam.entitlement-jail.ProbeService_bookmarks_app_scope\",\n        \"entitlements\": {\n          \"com.apple.security.app-sandbox\": true,\n          \"com.apple.security.files.bookmarks.app-scope\": true\n        },\n        \"entitlements_error\": null,\n        \"kind\": \"probe\",\n        \"label\": \"bookmarks app scope\",\n        \"profile_id\": \"bookmarks_app_scope\",\n        \"risk_reasons\": [],\n        \"risk_tier\": 0,\n        \"service_name\": \"ProbeService_bookmarks_app_scope\",\n        \"tags\": [\n          \"bookmarks_app_scope\",\n          \"probe\",\n          \"sandbox\"\n        ]\n      },\n      {\n        \"bundle_id\": \"com.yourteam.entitlement-jail.ProbeService_debuggable\",\n        \"entitlements\": {\n          \"com.apple.security.app-sandbox\": true,\n          \"com.apple.security.cs.disable-library-validation\": true,\n          \"com.apple.security.get-task-allow\": true\n        },\n        \"entitlements_error\": null,\n        \"kind\": \"probe\",\n        \"label\": \"debuggable\",\n        \"profile_id\": \"debuggable\",\n        \"risk_reasons\": [\n          \"get_task_allow\",\n          \"disable_library_validation\"\n        ],\n        \"risk_tier\": 1,\n        \"service_name\": \"ProbeService_debuggable\",\n        \"tags\": [\n          \"debuggable\",\n          \"disable_library_validation\",\n          \"probe\",\n          \"sandbox\"\n        ]\n      },\n      {\n        \"bundle_id\": \"com.yourteam.entitlement-jail.ProbeService_downloads_rw\",\n        \"entitlements\": {\n          \"com.apple.security.app-sandbox\": true,\n          \"com.apple.security.files.downloads.read-write\": true\n        },\n        \"entitlements_error\": null,\n        \"kind\": \"probe\",\n        \"label\": \"downloads rw\",\n        \"profile_id\": \"downloads_rw\",\n        \"risk_reasons\": [],\n        \"risk_tier\": 0,\n        \"service_name\": \"ProbeService_downloads_rw\",\n        \"tags\": [\n          \"downloads_rw\",\n          \"probe\",\n          \"sandbox\"\n        ]\n      },\n      {\n        \"bundle_id\": \"com.yourteam.entitlement-jail.ProbeService_dyld_env_enabled\",\n        \"entitlements\": {\n          \"com.apple.security.app-sandbox\": true,\n          \"com.apple.security.cs.allow-dyld-environment-variables\": true\n        },\n        \"entitlements_error\": null,\n        \"kind\": \"probe\",\n        \"label\": \"dyld env enabled\",\n        \"profile_id\": \"dyld_env_enabled\",\n        \"risk_reasons\": [\n          \"allow_dyld_env\"\n        ],\n        \"risk_tier\": 2,\n        \"service_name\": \"ProbeService_dyld_env_enabled\",\n        \"tags\": [\n          \"dyld_env\",\n          \"probe\",\n          \"sandbox\"\n        ]\n      },\n      {\n        \"bundle_id\": \"com.yourteam.entitlement-jail.ProbeService_fully_injectable\",\n        \"entitlements\": {\n          \"com.apple.security.app-sandbox\": true,\n          \"com.apple.security.cs.allow-dyld-environment-variables\": true,\n          \"com.apple.security.cs.allow-jit\": true,\n          \"com.apple.security.cs.allow-unsigned-executable-memory\": true,\n          \"com.apple.security.cs.disable-library-validation\": true,\n          \"com.apple.security.get-task-allow\": true\n        },\n        \"entitlements_error\": null,\n        \"kind\": \"probe\",\n        \"label\": \"fully injectable\",\n        \"profile_id\": \"fully_injectable\",\n        \"risk_reasons\": [\n          \"allow_dyld_env\",\n          \"allow_jit\",\n          \"allow_unsigned_exec_mem\"\n        ],\n        \"risk_tier\": 2,\n        \"service_name\": \"ProbeService_fully_injectable\",\n        \"tags\": [\n          \"debuggable\",\n          \"disable_library_validation\",\n          \"dyld_env\",\n          \"jit\",\n          \"probe\",\n          \"rwx_legacy\",\n          \"sandbox\"\n        ]\n      },\n      {\n        \"bundle_id\": \"com.yourteam.entitlement-jail.ProbeService_jit_map_jit\",\n        \"entitlements\": {\n          \"com.apple.security.app-sandbox\": true,\n          \"com.apple.security.cs.allow-jit\": true\n        },\n        \"entitlements_error\": null,\n        \"kind\": \"probe\",\n        \"label\": \"jit map jit\",\n        \"profile_id\": \"jit_map_jit\",\n        \"risk_reasons\": [\n          \"allow_jit\"\n        ],\n        \"risk_tier\": 2,\n        \"service_name\": \"ProbeService_jit_map_jit\",\n        \"tags\": [\n          \"jit\",\n          \"probe\",\n          \"sandbox\"\n        ]\n      },\n      {\n        \"bundle_id\": \"com.yourteam.entitlement-jail.ProbeService_jit_rwx_legacy\",\n        \"entitlements\": {\n          \"com.apple.security.app-sandbox\": true,\n          \"com.apple.security.cs.allow-unsigned-executable-memory\": true\n        },\n        \"entitlements_error\": null,\n        \"kind\": \"probe\",\n        \"label\": \"jit rwx legacy\",\n        \"profile_id\": \"jit_rwx_legacy\",\n        \"risk_reasons\": [\n          \"allow_unsigned_exec_mem\"\n        ],\n        \"risk_tier\": 2,\n        \"service_name\": \"ProbeService_jit_rwx_legacy\",\n        \"tags\": [\n          \"probe\",\n          \"rwx_legacy\",\n          \"sandbox\"\n        ]\n      },\n      {\n        \"bundle_id\": \"com.yourteam.entitlement-jail.ProbeService_minimal\",\n        \"entitlements\": {\n          \"com.apple.security.app-sandbox\": true\n        },\n        \"entitlements_error\": null,\n        \"kind\": \"probe\",\n        \"label\": \"minimal\",\n        \"profile_id\": \"minimal\",\n        \"risk_reasons\": [],\n        \"risk_tier\": 0,\n        \"service_name\": \"ProbeService_minimal\",\n        \"tags\": [\n          \"baseline\",\n          \"probe\",\n          \"sandbox\"\n        ]\n      },\n      {\n        \"bundle_id\": \"com.yourteam.entitlement-jail.ProbeService_net_client\",\n        \"entitlements\": {\n          \"com.apple.security.app-sandbox\": true,\n          \"com.apple.security.network.client\": true\n        },\n        \"entitlements_error\": null,\n        \"kind\": \"probe\",\n        \"label\": \"net client\",\n        \"profile_id\": \"net_client\",\n        \"risk_reasons\": [],\n        \"risk_tier\": 0,\n        \"service_name\": \"ProbeService_net_client\",\n        \"tags\": [\n          \"network_client\",\n          \"probe\",\n          \"sandbox\"\n        ]\n      },\n      {\n        \"bundle_id\": \"com.yourteam.entitlement-jail.ProbeService_plugin_host_relaxed\",\n        \"entitlements\": {\n          \"com.apple.security.app-sandbox\": true,\n          \"com.apple.security.cs.disable-library-validation\": true\n        },\n        \"entitlements_error\": null,\n        \"kind\": \"probe\",\n        \"label\": \"plugin host relaxed\",\n        \"profile_id\": \"plugin_host_relaxed\",\n        \"risk_reasons\": [\n          \"disable_library_validation\"\n        ],\n        \"risk_tier\": 1,\n        \"service_name\": \"ProbeService_plugin_host_relaxed\",\n        \"tags\": [\n          \"disable_library_validation\",\n          \"probe\",\n          \"sandbox\"\n        ]\n      },\n      {\n        \"bundle_id\": \"com.yourteam.entitlement-jail.QuarantineLab_bookmarks_app_scope\",\n        \"entitlements\": {\n          \"com.apple.security.app-sandbox\": true,\n          \"com.apple.security.files.bookmarks.app-scope\": true\n        },\n        \"entitlements_error\": null,\n        \"kind\": \"quarantine\",\n        \"label\": \"quarantine bookmarks app scope\",\n        \"profile_id\": \"quarantine_bookmarks_app_scope\",\n        \"risk_reasons\": [],\n        \"risk_tier\": 0,\n        \"service_name\": \"QuarantineLab_bookmarks_app_scope\",\n        \"tags\": [\n          \"bookmarks_app_scope\",\n          \"quarantine\",\n          \"sandbox\"\n        ]\n      },\n      {\n        \"bundle_id\": \"com.yourteam.entitlement-jail.QuarantineLab_default\",\n        \"entitlements\": {\n          \"com.apple.security.app-sandbox\": true\n        },\n        \"entitlements_error\": null,\n        \"kind\": \"quarantine\",\n        \"label\": \"quarantine default\",\n        \"profile_id\": \"quarantine_default\",\n        \"risk_reasons\": [],\n        \"risk_tier\": 0,\n        \"service_name\": \"QuarantineLab_default\",\n        \"tags\": [\n          \"baseline\",\n          \"quarantine\",\n          \"sandbox\"\n        ]\n      },\n      {\n        \"bundle_id\": \"com.yourteam.entitlement-jail.QuarantineLab_downloads_rw\",\n        \"entitlements\": {\n          \"com.apple.security.app-sandbox\": true,\n          \"com.apple.security.files.downloads.read-write\": true\n        },\n        \"entitlements_error\": null,\n        \"kind\": \"quarantine\",\n        \"label\": \"quarantine downloads rw\",\n        \"profile_id\": \"quarantine_downloads_rw\",\n        \"risk_reasons\": [],\n        \"risk_tier\": 0,\n        \"service_name\": \"QuarantineLab_downloads_rw\",\n        \"tags\": [\n          \"downloads_rw\",\n          \"quarantine\",\n          \"sandbox\"\n        ]\n      },\n      {\n        \"bundle_id\": \"com.yourteam.entitlement-jail.QuarantineLab_net_client\",\n        \"entitlements\": {\n          \"com.apple.security.app-sandbox\": true,\n          \"com.apple.security.network.client\": true\n        },\n        \"entitlements_error\": null,\n        \"kind\": \"quarantine\",\n        \"label\": \"quarantine net client\",\n        \"profile_id\": \"quarantine_net_client\",\n        \"risk_reasons\": [],\n        \"risk_tier\": 0,\n        \"service_name\": \"QuarantineLab_net_client\",\n        \"tags\": [\n          \"network_client\",\n          \"quarantine\",\n          \"sandbox\"\n        ]\n      },\n      {\n        \"bundle_id\": \"com.yourteam.entitlement-jail.QuarantineLab_user_selected_executable\",\n        \"entitlements\": {\n          \"com.apple.security.app-sandbox\": true,\n          \"com.apple.security.files.user-selected.executable\": true\n        },\n        \"entitlements_error\": null,\n        \"kind\": \"quarantine\",\n        \"label\": \"quarantine user selected executable\",\n        \"profile_id\": \"quarantine_user_selected_executable\",\n        \"risk_reasons\": [],\n        \"risk_tier\": 0,\n        \"service_name\": \"QuarantineLab_user_selected_executable\",\n        \"tags\": [\n          \"quarantine\",\n          \"sandbox\",\n          \"user_selected_executable\"\n        ]\n      },\n      {\n        \"bundle_id\": \"com.yourteam.entitlement-jail.ProbeService_user_selected_executable\",\n        \"entitlements\": {\n          \"com.apple.security.app-sandbox\": true,\n          \"com.apple.security.files.user-selected.executable\": true\n        },\n        \"entitlements_error\": null,\n        \"kind\": \"probe\",\n        \"label\": \"user selected executable\",\n        \"profile_id\": \"user_selected_executable\",\n        \"risk_reasons\": [],\n        \"risk_tier\": 0,\n        \"service_name\": \"ProbeService_user_selected_executable\",\n        \"tags\": [\n          \"probe\",\n          \"sandbox\",\n          \"user_selected_executable\"\n        ]\n      }\n    ],\n    \"profiles_path\": \"/Users/achyland/Desktop/VM-BRIDGE/SANDBOX_LORE/book/tools/entitlement/EntitlementJail.app/Contents/Resources/Evidence/profiles.json\"\n  },\n  \"generated_at_unix_ms\": 1766618482835,\n  \"kind\": \"profiles_report\",\n  \"result\": {\n    \"errno\": null,\n    \"error\": null,\n    \"exit_code\": 0,\n    \"normalized_outcome\": null,\n    \"ok\": true,\n    \"rc\": null,\n    \"stderr\": null,\n    \"stdout\": null\n  },\n  \"schema_version\": 1\n}\n",
      "stderr": ""
    },
    {
      "command": [
        "book/tools/entitlement/EntitlementJail.app/Contents/MacOS/entitlement-jail",
        "list-services"
      ],
      "exit_code": 0,
      "stdout": "{\n  \"data\": {\n    \"generated_at\": \"2025-12-24T23:06:51Z\",\n    \"profiles_path\": \"/Users/achyland/Desktop/VM-BRIDGE/SANDBOX_LORE/book/tools/entitlement/EntitlementJail.app/Contents/Resources/Evidence/profiles.json\",\n    \"services\": [\n      {\n        \"bundle_id\": \"com.yourteam.entitlement-jail.ProbeService_bookmarks_app_scope\",\n        \"entitlements\": {\n          \"com.apple.security.app-sandbox\": true,\n          \"com.apple.security.files.bookmarks.app-scope\": true\n        },\n        \"entitlements_error\": null,\n        \"kind\": \"probe\",\n        \"label\": \"bookmarks app scope\",\n        \"profile_id\": \"bookmarks_app_scope\",\n        \"risk_reasons\": [],\n        \"risk_tier\": 0,\n        \"service_name\": \"ProbeService_bookmarks_app_scope\",\n        \"tags\": [\n          \"bookmarks_app_scope\",\n          \"probe\",\n          \"sandbox\"\n        ]\n      },\n      {\n        \"bundle_id\": \"com.yourteam.entitlement-jail.ProbeService_debuggable\",\n        \"entitlements\": {\n          \"com.apple.security.app-sandbox\": true,\n          \"com.apple.security.cs.disable-library-validation\": true,\n          \"com.apple.security.get-task-allow\": true\n        },\n        \"entitlements_error\": null,\n        \"kind\": \"probe\",\n        \"label\": \"debuggable\",\n        \"profile_id\": \"debuggable\",\n        \"risk_reasons\": [\n          \"get_task_allow\",\n          \"disable_library_validation\"\n        ],\n        \"risk_tier\": 1,\n        \"service_name\": \"ProbeService_debuggable\",\n        \"tags\": [\n          \"debuggable\",\n          \"disable_library_validation\",\n          \"probe\",\n          \"sandbox\"\n        ]\n      },\n      {\n        \"bundle_id\": \"com.yourteam.entitlement-jail.ProbeService_downloads_rw\",\n        \"entitlements\": {\n          \"com.apple.security.app-sandbox\": true,\n          \"com.apple.security.files.downloads.read-write\": true\n        },\n        \"entitlements_error\": null,\n        \"kind\": \"probe\",\n        \"label\": \"downloads rw\",\n        \"profile_id\": \"downloads_rw\",\n        \"risk_reasons\": [],\n        \"risk_tier\": 0,\n        \"service_name\": \"ProbeService_downloads_rw\",\n        \"tags\": [\n          \"downloads_rw\",\n          \"probe\",\n          \"sandbox\"\n        ]\n      },\n      {\n        \"bundle_id\": \"com.yourteam.entitlement-jail.ProbeService_dyld_env_enabled\",\n        \"entitlements\": {\n          \"com.apple.security.app-sandbox\": true,\n          \"com.apple.security.cs.allow-dyld-environment-variables\": true\n        },\n        \"entitlements_error\": null,\n        \"kind\": \"probe\",\n        \"label\": \"dyld env enabled\",\n        \"profile_id\": \"dyld_env_enabled\",\n        \"risk_reasons\": [\n          \"allow_dyld_env\"\n        ],\n        \"risk_tier\": 2,\n        \"service_name\": \"ProbeService_dyld_env_enabled\",\n        \"tags\": [\n          \"dyld_env\",\n          \"probe\",\n          \"sandbox\"\n        ]\n      },\n      {\n        \"bundle_id\": \"com.yourteam.entitlement-jail.ProbeService_fully_injectable\",\n        \"entitlements\": {\n          \"com.apple.security.app-sandbox\": true,\n          \"com.apple.security.cs.allow-dyld-environment-variables\": true,\n          \"com.apple.security.cs.allow-jit\": true,\n          \"com.apple.security.cs.allow-unsigned-executable-memory\": true,\n          \"com.apple.security.cs.disable-library-validation\": true,\n          \"com.apple.security.get-task-allow\": true\n        },\n        \"entitlements_error\": null,\n        \"kind\": \"probe\",\n        \"label\": \"fully injectable\",\n        \"profile_id\": \"fully_injectable\",\n        \"risk_reasons\": [\n          \"allow_dyld_env\",\n          \"allow_jit\",\n          \"allow_unsigned_exec_mem\"\n        ],\n        \"risk_tier\": 2,\n        \"service_name\": \"ProbeService_fully_injectable\",\n        \"tags\": [\n          \"debuggable\",\n          \"disable_library_validation\",\n          \"dyld_env\",\n          \"jit\",\n          \"probe\",\n          \"rwx_legacy\",\n          \"sandbox\"\n        ]\n      },\n      {\n        \"bundle_id\": \"com.yourteam.entitlement-jail.ProbeService_jit_map_jit\",\n        \"entitlements\": {\n          \"com.apple.security.app-sandbox\": true,\n          \"com.apple.security.cs.allow-jit\": true\n        },\n        \"entitlements_error\": null,\n        \"kind\": \"probe\",\n        \"label\": \"jit map jit\",\n        \"profile_id\": \"jit_map_jit\",\n        \"risk_reasons\": [\n          \"allow_jit\"\n        ],\n        \"risk_tier\": 2,\n        \"service_name\": \"ProbeService_jit_map_jit\",\n        \"tags\": [\n          \"jit\",\n          \"probe\",\n          \"sandbox\"\n        ]\n      },\n      {\n        \"bundle_id\": \"com.yourteam.entitlement-jail.ProbeService_jit_rwx_legacy\",\n        \"entitlements\": {\n          \"com.apple.security.app-sandbox\": true,\n          \"com.apple.security.cs.allow-unsigned-executable-memory\": true\n        },\n        \"entitlements_error\": null,\n        \"kind\": \"probe\",\n        \"label\": \"jit rwx legacy\",\n        \"profile_id\": \"jit_rwx_legacy\",\n        \"risk_reasons\": [\n          \"allow_unsigned_exec_mem\"\n        ],\n        \"risk_tier\": 2,\n        \"service_name\": \"ProbeService_jit_rwx_legacy\",\n        \"tags\": [\n          \"probe\",\n          \"rwx_legacy\",\n          \"sandbox\"\n        ]\n      },\n      {\n        \"bundle_id\": \"com.yourteam.entitlement-jail.ProbeService_minimal\",\n        \"entitlements\": {\n          \"com.apple.security.app-sandbox\": true\n        },\n        \"entitlements_error\": null,\n        \"kind\": \"probe\",\n        \"label\": \"minimal\",\n        \"profile_id\": \"minimal\",\n        \"risk_reasons\": [],\n        \"risk_tier\": 0,\n        \"service_name\": \"ProbeService_minimal\",\n        \"tags\": [\n          \"baseline\",\n          \"probe\",\n          \"sandbox\"\n        ]\n      },\n      {\n        \"bundle_id\": \"com.yourteam.entitlement-jail.ProbeService_net_client\",\n        \"entitlements\": {\n          \"com.apple.security.app-sandbox\": true,\n          \"com.apple.security.network.client\": true\n        },\n        \"entitlements_error\": null,\n        \"kind\": \"probe\",\n        \"label\": \"net client\",\n        \"profile_id\": \"net_client\",\n        \"risk_reasons\": [],\n        \"risk_tier\": 0,\n        \"service_name\": \"ProbeService_net_client\",\n        \"tags\": [\n          \"network_client\",\n          \"probe\",\n          \"sandbox\"\n        ]\n      },\n      {\n        \"bundle_id\": \"com.yourteam.entitlement-jail.ProbeService_plugin_host_relaxed\",\n        \"entitlements\": {\n          \"com.apple.security.app-sandbox\": true,\n          \"com.apple.security.cs.disable-library-validation\": true\n        },\n        \"entitlements_error\": null,\n        \"kind\": \"probe\",\n        \"label\": \"plugin host relaxed\",\n        \"profile_id\": \"plugin_host_relaxed\",\n        \"risk_reasons\": [\n          \"disable_library_validation\"\n        ],\n        \"risk_tier\": 1,\n        \"service_name\": \"ProbeService_plugin_host_relaxed\",\n        \"tags\": [\n          \"disable_library_validation\",\n          \"probe\",\n          \"sandbox\"\n        ]\n      },\n      {\n        \"bundle_id\": \"com.yourteam.entitlement-jail.QuarantineLab_bookmarks_app_scope\",\n        \"entitlements\": {\n          \"com.apple.security.app-sandbox\": true,\n          \"com.apple.security.files.bookmarks.app-scope\": true\n        },\n        \"entitlements_error\": null,\n        \"kind\": \"quarantine\",\n        \"label\": \"quarantine bookmarks app scope\",\n        \"profile_id\": \"quarantine_bookmarks_app_scope\",\n        \"risk_reasons\": [],\n        \"risk_tier\": 0,\n        \"service_name\": \"QuarantineLab_bookmarks_app_scope\",\n        \"tags\": [\n          \"bookmarks_app_scope\",\n          \"quarantine\",\n          \"sandbox\"\n        ]\n      },\n      {\n        \"bundle_id\": \"com.yourteam.entitlement-jail.QuarantineLab_default\",\n        \"entitlements\": {\n          \"com.apple.security.app-sandbox\": true\n        },\n        \"entitlements_error\": null,\n        \"kind\": \"quarantine\",\n        \"label\": \"quarantine default\",\n        \"profile_id\": \"quarantine_default\",\n        \"risk_reasons\": [],\n        \"risk_tier\": 0,\n        \"service_name\": \"QuarantineLab_default\",\n        \"tags\": [\n          \"baseline\",\n          \"quarantine\",\n          \"sandbox\"\n        ]\n      },\n      {\n        \"bundle_id\": \"com.yourteam.entitlement-jail.QuarantineLab_downloads_rw\",\n        \"entitlements\": {\n          \"com.apple.security.app-sandbox\": true,\n          \"com.apple.security.files.downloads.read-write\": true\n        },\n        \"entitlements_error\": null,\n        \"kind\": \"quarantine\",\n        \"label\": \"quarantine downloads rw\",\n        \"profile_id\": \"quarantine_downloads_rw\",\n        \"risk_reasons\": [],\n        \"risk_tier\": 0,\n        \"service_name\": \"QuarantineLab_downloads_rw\",\n        \"tags\": [\n          \"downloads_rw\",\n          \"quarantine\",\n          \"sandbox\"\n        ]\n      },\n      {\n        \"bundle_id\": \"com.yourteam.entitlement-jail.QuarantineLab_net_client\",\n        \"entitlements\": {\n          \"com.apple.security.app-sandbox\": true,\n          \"com.apple.security.network.client\": true\n        },\n        \"entitlements_error\": null,\n        \"kind\": \"quarantine\",\n        \"label\": \"quarantine net client\",\n        \"profile_id\": \"quarantine_net_client\",\n        \"risk_reasons\": [],\n        \"risk_tier\": 0,\n        \"service_name\": \"QuarantineLab_net_client\",\n        \"tags\": [\n          \"network_client\",\n          \"quarantine\",\n          \"sandbox\"\n        ]\n      },\n      {\n        \"bundle_id\": \"com.yourteam.entitlement-jail.QuarantineLab_user_selected_executable\",\n        \"entitlements\": {\n          \"com.apple.security.app-sandbox\": true,\n          \"com.apple.security.files.user-selected.executable\": true\n        },\n        \"entitlements_error\": null,\n        \"kind\": \"quarantine\",\n        \"label\": \"quarantine user selected executable\",\n        \"profile_id\": \"quarantine_user_selected_executable\",\n        \"risk_reasons\": [],\n        \"risk_tier\": 0,\n        \"service_name\": \"QuarantineLab_user_selected_executable\",\n        \"tags\": [\n          \"quarantine\",\n          \"sandbox\",\n          \"user_selected_executable\"\n        ]\n      },\n      {\n        \"bundle_id\": \"com.yourteam.entitlement-jail.ProbeService_user_selected_executable\",\n        \"entitlements\": {\n          \"com.apple.security.app-sandbox\": true,\n          \"com.apple.security.files.user-selected.executable\": true\n        },\n        \"entitlements_error\": null,\n        \"kind\": \"probe\",\n        \"label\": \"user selected executable\",\n        \"profile_id\": \"user_selected_executable\",\n        \"risk_reasons\": [],\n        \"risk_tier\": 0,\n        \"service_name\": \"ProbeService_user_selected_executable\",\n        \"tags\": [\n          \"probe\",\n          \"sandbox\",\n          \"user_selected_executable\"\n        ]\n      }\n    ]\n  },\n  \"generated_at_unix_ms\": 1766618482844,\n  \"kind\": \"services_report\",\n  \"result\": {\n    \"errno\": null,\n    \"error\": null,\n    \"exit_code\": 0,\n    \"normalized_outcome\": null,\n    \"ok\": true,\n    \"rc\": null,\n    \"stderr\": null,\n    \"stdout\": null\n  },\n  \"schema_version\": 1\n}\n",
      "stderr": ""
    },
    {
      "command": [
        "book/tools/entitlement/EntitlementJail.app/Contents/MacOS/entitlement-jail",
        "show-profile",
        "minimal"
      ],
      "exit_code": 0,
      "stdout": "{\n  \"data\": {\n    \"profile\": {\n      \"bundle_id\": \"com.yourteam.entitlement-jail.ProbeService_minimal\",\n      \"entitlements\": {\n        \"com.apple.security.app-sandbox\": true\n      },\n      \"entitlements_error\": null,\n      \"kind\": \"probe\",\n      \"label\": \"minimal\",\n      \"profile_id\": \"minimal\",\n      \"risk_reasons\": [],\n      \"risk_tier\": 0,\n      \"service_name\": \"ProbeService_minimal\",\n      \"tags\": [\n        \"baseline\",\n        \"probe\",\n        \"sandbox\"\n      ]\n    },\n    \"profiles_path\": \"/Users/achyland/Desktop/VM-BRIDGE/SANDBOX_LORE/book/tools/entitlement/EntitlementJail.app/Contents/Resources/Evidence/profiles.json\"\n  },\n  \"generated_at_unix_ms\": 1766618482853,\n  \"kind\": \"profile_report\",\n  \"result\": {\n    \"errno\": null,\n    \"error\": null,\n    \"exit_code\": 0,\n    \"normalized_outcome\": null,\n    \"ok\": true,\n    \"rc\": null,\n    \"stderr\": null,\n    \"stdout\": null\n  },\n  \"schema_version\": 1\n}\n",
      "stderr": ""
    },
    {
      "command": [
        "book/tools/entitlement/EntitlementJail.app/Contents/MacOS/entitlement-jail",
        "describe-service",
        "minimal"
      ],
      "exit_code": 0,
      "stdout": "{\n  \"data\": {\n    \"capabilities\": {\n      \"app_support_dir\": \"/Users/achyland/Library/Containers/com.yourteam.entitlement-jail/Data/Library/Containers/com.yourteam.entitlement-jail.ProbeService_minimal/Data/Library/Application Support\",\n      \"caches_dir\": \"/Users/achyland/Library/Containers/com.yourteam.entitlement-jail/Data/Library/Containers/com.yourteam.entitlement-jail.ProbeService_minimal/Data/Library/Caches\",\n      \"desktop_dir\": \"/Users/achyland/Library/Containers/com.yourteam.entitlement-jail/Data/Library/Containers/com.yourteam.entitlement-jail.ProbeService_minimal/Data/Desktop\",\n      \"documents_dir\": \"/Users/achyland/Library/Containers/com.yourteam.entitlement-jail/Data/Library/Containers/com.yourteam.entitlement-jail.ProbeService_minimal/Data/Documents\",\n      \"downloads_dir\": \"/Users/achyland/Library/Containers/com.yourteam.entitlement-jail/Data/Library/Containers/com.yourteam.entitlement-jail.ProbeService_minimal/Data/Downloads\",\n      \"has_allow_dyld_env\": false,\n      \"has_allow_jit\": false,\n      \"has_allow_unsigned_exec_mem\": false,\n      \"has_app_sandbox\": true,\n      \"has_bookmarks_app_scope\": false,\n      \"has_disable_library_validation\": false,\n      \"has_downloads_rw\": false,\n      \"has_get_task_allow\": false,\n      \"has_network_client\": false,\n      \"has_user_selected_executable\": false,\n      \"has_user_selected_read_only\": false,\n      \"has_user_selected_read_write\": false,\n      \"home_dir\": \"/Users/achyland/Library/Containers/com.yourteam.entitlement-jail/Data/Library/Containers/com.yourteam.entitlement-jail.ProbeService_minimal/Data\",\n      \"prefs_path_guess\": \"/Users/achyland/Library/Containers/com.yourteam.entitlement-jail/Data/Library/Containers/com.yourteam.entitlement-jail.ProbeService_minimal/Data/Library/Preferences/com.yourteam.entitlement-jail.ProbeService_minimal.plist\",\n      \"tmp_dir\": \"/Users/achyland/Library/Containers/com.yourteam.entitlement-jail/Data/Library/Containers/com.yourteam.entitlement-jail.ProbeService_minimal/Data/tmp\"\n    },\n    \"capabilities_source\": \"static\",\n    \"service\": {\n      \"bundle_id\": \"com.yourteam.entitlement-jail.ProbeService_minimal\",\n      \"entitlements\": {\n        \"com.apple.security.app-sandbox\": true\n      },\n      \"entitlements_error\": null,\n      \"kind\": \"probe\",\n      \"label\": \"minimal\",\n      \"profile_id\": \"minimal\",\n      \"risk_reasons\": [],\n      \"risk_tier\": 0,\n      \"service_name\": \"ProbeService_minimal\",\n      \"tags\": [\n        \"baseline\",\n        \"probe\",\n        \"sandbox\"\n      ]\n    }\n  },\n  \"generated_at_unix_ms\": 1766618482861,\n  \"kind\": \"describe_service_report\",\n  \"result\": {\n    \"errno\": null,\n    \"error\": null,\n    \"exit_code\": 0,\n    \"normalized_outcome\": null,\n    \"ok\": true,\n    \"rc\": null,\n    \"stderr\": null,\n    \"stdout\": null\n  },\n  \"schema_version\": 1\n}\n",
      "stderr": ""
    },
    {
      "command": [
        "book/tools/entitlement/EntitlementJail.app/Contents/MacOS/entitlement-jail",
        "show-profile",
        "bookmarks_app_scope"
      ],
      "exit_code": 0,
      "stdout": "{\n  \"data\": {\n    \"profile\": {\n      \"bundle_id\": \"com.yourteam.entitlement-jail.ProbeService_bookmarks_app_scope\",\n      \"entitlements\": {\n        \"com.apple.security.app-sandbox\": true,\n        \"com.apple.security.files.bookmarks.app-scope\": true\n      },\n      \"entitlements_error\": null,\n      \"kind\": \"probe\",\n      \"label\": \"bookmarks app scope\",\n      \"profile_id\": \"bookmarks_app_scope\",\n      \"risk_reasons\": [],\n      \"risk_tier\": 0,\n      \"service_name\": \"ProbeService_bookmarks_app_scope\",\n      \"tags\": [\n        \"bookmarks_app_scope\",\n        \"probe\",\n        \"sandbox\"\n      ]\n    },\n    \"profiles_path\": \"/Users/achyland/Desktop/VM-BRIDGE/SANDBOX_LORE/book/tools/entitlement/EntitlementJail.app/Contents/Resources/Evidence/profiles.json\"\n  },\n  \"generated_at_unix_ms\": 1766618482870,\n  \"kind\": \"profile_report\",\n  \"result\": {\n    \"errno\": null,\n    \"error\": null,\n    \"exit_code\": 0,\n    \"normalized_outcome\": null,\n    \"ok\": true,\n    \"rc\": null,\n    \"stderr\": null,\n    \"stdout\": null\n  },\n  \"schema_version\": 1\n}\n",
      "stderr": ""
    },
    {
      "command": [
        "book/tools/entitlement/EntitlementJail.app/Contents/MacOS/entitlement-jail",
        "describe-service",
        "bookmarks_app_scope"
      ],
      "exit_code": 0,
      "stdout": "{\n  \"data\": {\n    \"capabilities\": {\n      \"app_support_dir\": \"/Users/achyland/Library/Containers/com.yourteam.entitlement-jail/Data/Library/Containers/com.yourteam.entitlement-jail.ProbeService_bookmarks_app_scope/Data/Library/Application Support\",\n      \"caches_dir\": \"/Users/achyland/Library/Containers/com.yourteam.entitlement-jail/Data/Library/Containers/com.yourteam.entitlement-jail.ProbeService_bookmarks_app_scope/Data/Library/Caches\",\n      \"desktop_dir\": \"/Users/achyland/Library/Containers/com.yourteam.entitlement-jail/Data/Library/Containers/com.yourteam.entitlement-jail.ProbeService_bookmarks_app_scope/Data/Desktop\",\n      \"documents_dir\": \"/Users/achyland/Library/Containers/com.yourteam.entitlement-jail/Data/Library/Containers/com.yourteam.entitlement-jail.ProbeService_bookmarks_app_scope/Data/Documents\",\n      \"downloads_dir\": \"/Users/achyland/Library/Containers/com.yourteam.entitlement-jail/Data/Library/Containers/com.yourteam.entitlement-jail.ProbeService_bookmarks_app_scope/Data/Downloads\",\n      \"has_allow_dyld_env\": false,\n      \"has_allow_jit\": false,\n      \"has_allow_unsigned_exec_mem\": false,\n      \"has_app_sandbox\": true,\n      \"has_bookmarks_app_scope\": true,\n      \"has_disable_library_validation\": false,\n      \"has_downloads_rw\": false,\n      \"has_get_task_allow\": false,\n      \"has_network_client\": false,\n      \"has_user_selected_executable\": false,\n      \"has_user_selected_read_only\": false,\n      \"has_user_selected_read_write\": false,\n      \"home_dir\": \"/Users/achyland/Library/Containers/com.yourteam.entitlement-jail/Data/Library/Containers/com.yourteam.entitlement-jail.ProbeService_bookmarks_app_scope/Data\",\n      \"prefs_path_guess\": \"/Users/achyland/Library/Containers/com.yourteam.entitlement-jail/Data/Library/Containers/com.yourteam.entitlement-jail.ProbeService_bookmarks_app_scope/Data/Library/Preferences/com.yourteam.entitlement-jail.ProbeService_bookmarks_app_scope.plist\",\n      \"tmp_dir\": \"/Users/achyland/Library/Containers/com.yourteam.entitlement-jail/Data/Library/Containers/com.yourteam.entitlement-jail.ProbeService_bookmarks_app_scope/Data/tmp\"\n    },\n    \"capabilities_source\": \"static\",\n    \"service\": {\n      \"bundle_id\": \"com.yourteam.entitlement-jail.ProbeService_bookmarks_app_scope\",\n      \"entitlements\": {\n        \"com.apple.security.app-sandbox\": true,\n        \"com.apple.security.files.bookmarks.app-scope\": true\n      },\n      \"entitlements_error\": null,\n      \"kind\": \"probe\",\n      \"label\": \"bookmarks app scope\",\n      \"profile_id\": \"bookmarks_app_scope\",\n      \"risk_reasons\": [],\n      \"risk_tier\": 0,\n      \"service_name\": \"ProbeService_bookmarks_app_scope\",\n      \"tags\": [\n        \"bookmarks_app_scope\",\n        \"probe\",\n        \"sandbox\"\n      ]\n    }\n  },\n  \"generated_at_unix_ms\": 1766618482879,\n  \"kind\": \"describe_service_report\",\n  \"result\": {\n    \"errno\": null,\n    \"error\": null,\n    \"exit_code\": 0,\n    \"normalized_outcome\": null,\n    \"ok\": true,\n    \"rc\": null,\n    \"stderr\": null,\n    \"stdout\": null\n  },\n  \"schema_version\": 1\n}\n",
      "stderr": ""
    },
    {
      "command": [
        "book/tools/entitlement/EntitlementJail.app/Contents/MacOS/entitlement-jail",
        "show-profile",
        "downloads_rw"
      ],
      "exit_code": 0,
      "stdout": "{\n  \"data\": {\n    \"profile\": {\n      \"bundle_id\": \"com.yourteam.entitlement-jail.ProbeService_downloads_rw\",\n      \"entitlements\": {\n        \"com.apple.security.app-sandbox\": true,\n        \"com.apple.security.files.downloads.read-write\": true\n      },\n      \"entitlements_error\": null,\n      \"kind\": \"probe\",\n      \"label\": \"downloads rw\",\n      \"profile_id\": \"downloads_rw\",\n      \"risk_reasons\": [],\n      \"risk_tier\": 0,\n      \"service_name\": \"ProbeService_downloads_rw\",\n      \"tags\": [\n        \"downloads_rw\",\n        \"probe\",\n        \"sandbox\"\n      ]\n    },\n    \"profiles_path\": \"/Users/achyland/Desktop/VM-BRIDGE/SANDBOX_LORE/book/tools/entitlement/EntitlementJail.app/Contents/Resources/Evidence/profiles.json\"\n  },\n  \"generated_at_unix_ms\": 1766618482887,\n  \"kind\": \"profile_report\",\n  \"result\": {\n    \"errno\": null,\n    \"error\": null,\n    \"exit_code\": 0,\n    \"normalized_outcome\": null,\n    \"ok\": true,\n    \"rc\": null,\n    \"stderr\": null,\n    \"stdout\": null\n  },\n  \"schema_version\": 1\n}\n",
      "stderr": ""
    },
    {
      "command": [
        "book/tools/entitlement/EntitlementJail.app/Contents/MacOS/entitlement-jail",
        "describe-service",
        "downloads_rw"
      ],
      "exit_code": 0,
      "stdout": "{\n  \"data\": {\n    \"capabilities\": {\n      \"app_support_dir\": \"/Users/achyland/Library/Containers/com.yourteam.entitlement-jail/Data/Library/Containers/com.yourteam.entitlement-jail.ProbeService_downloads_rw/Data/Library/Application Support\",\n      \"caches_dir\": \"/Users/achyland/Library/Containers/com.yourteam.entitlement-jail/Data/Library/Containers/com.yourteam.entitlement-jail.ProbeService_downloads_rw/Data/Library/Caches\",\n      \"desktop_dir\": \"/Users/achyland/Library/Containers/com.yourteam.entitlement-jail/Data/Library/Containers/com.yourteam.entitlement-jail.ProbeService_downloads_rw/Data/Desktop\",\n      \"documents_dir\": \"/Users/achyland/Library/Containers/com.yourteam.entitlement-jail/Data/Library/Containers/com.yourteam.entitlement-jail.ProbeService_downloads_rw/Data/Documents\",\n      \"downloads_dir\": \"/Users/achyland/Library/Containers/com.yourteam.entitlement-jail/Data/Library/Containers/com.yourteam.entitlement-jail.ProbeService_downloads_rw/Data/Downloads\",\n      \"has_allow_dyld_env\": false,\n      \"has_allow_jit\": false,\n      \"has_allow_unsigned_exec_mem\": false,\n      \"has_app_sandbox\": true,\n      \"has_bookmarks_app_scope\": false,\n      \"has_disable_library_validation\": false,\n      \"has_downloads_rw\": true,\n      \"has_get_task_allow\": false,\n      \"has_network_client\": false,\n      \"has_user_selected_executable\": false,\n      \"has_user_selected_read_only\": false,\n      \"has_user_selected_read_write\": false,\n      \"home_dir\": \"/Users/achyland/Library/Containers/com.yourteam.entitlement-jail/Data/Library/Containers/com.yourteam.entitlement-jail.ProbeService_downloads_rw/Data\",\n      \"prefs_path_guess\": \"/Users/achyland/Library/Containers/com.yourteam.entitlement-jail/Data/Library/Containers/com.yourteam.entitlement-jail.ProbeService_downloads_rw/Data/Library/Preferences/com.yourteam.entitlement-jail.ProbeService_downloads_rw.plist\",\n      \"tmp_dir\": \"/Users/achyland/Library/Containers/com.yourteam.entitlement-jail/Data/Library/Containers/com.yourteam.entitlement-jail.ProbeService_downloads_rw/Data/tmp\"\n    },\n    \"capabilities_source\": \"static\",\n    \"service\": {\n      \"bundle_id\": \"com.yourteam.entitlement-jail.ProbeService_downloads_rw\",\n      \"entitlements\": {\n        \"com.apple.security.app-sandbox\": true,\n        \"com.apple.security.files.downloads.read-write\": true\n      },\n      \"entitlements_error\": null,\n      \"kind\": \"probe\",\n      \"label\": \"downloads rw\",\n      \"profile_id\": \"downloads_rw\",\n      \"risk_reasons\": [],\n      \"risk_tier\": 0,\n      \"service_name\": \"ProbeService_downloads_rw\",\n      \"tags\": [\n        \"downloads_rw\",\n        \"probe\",\n        \"sandbox\"\n      ]\n    }\n  },\n  \"generated_at_unix_ms\": 1766618482896,\n  \"kind\": \"describe_service_report\",\n  \"result\": {\n    \"errno\": null,\n    \"error\": null,\n    \"exit_code\": 0,\n    \"normalized_outcome\": null,\n    \"ok\": true,\n    \"rc\": null,\n    \"stderr\": null,\n    \"stdout\": null\n  },\n  \"schema_version\": 1\n}\n",
      "stderr": ""
    },
    {
      "command": [
        "book/tools/entitlement/EntitlementJail.app/Contents/MacOS/entitlement-jail",
        "show-profile",
        "net_client"
      ],
      "exit_code": 0,
      "stdout": "{\n  \"data\": {\n    \"profile\": {\n      \"bundle_id\": \"com.yourteam.entitlement-jail.ProbeService_net_client\",\n      \"entitlements\": {\n        \"com.apple.security.app-sandbox\": true,\n        \"com.apple.security.network.client\": true\n      },\n      \"entitlements_error\": null,\n      \"kind\": \"probe\",\n      \"label\": \"net client\",\n      \"profile_id\": \"net_client\",\n      \"risk_reasons\": [],\n      \"risk_tier\": 0,\n      \"service_name\": \"ProbeService_net_client\",\n      \"tags\": [\n        \"network_client\",\n        \"probe\",\n        \"sandbox\"\n      ]\n    },\n    \"profiles_path\": \"/Users/achyland/Desktop/VM-BRIDGE/SANDBOX_LORE/book/tools/entitlement/EntitlementJail.app/Contents/Resources/Evidence/profiles.json\"\n  },\n  \"generated_at_unix_ms\": 1766618482904,\n  \"kind\": \"profile_report\",\n  \"result\": {\n    \"errno\": null,\n    \"error\": null,\n    \"exit_code\": 0,\n    \"normalized_outcome\": null,\n    \"ok\": true,\n    \"rc\": null,\n    \"stderr\": null,\n    \"stdout\": null\n  },\n  \"schema_version\": 1\n}\n",
      "stderr": ""
    },
    {
      "command": [
        "book/tools/entitlement/EntitlementJail.app/Contents/MacOS/entitlement-jail",
        "describe-service",
        "net_client"
      ],
      "exit_code": 0,
      "stdout": "{\n  \"data\": {\n    \"capabilities\": {\n      \"app_support_dir\": \"/Users/achyland/Library/Containers/com.yourteam.entitlement-jail/Data/Library/Containers/com.yourteam.entitlement-jail.ProbeService_net_client/Data/Library/Application Support\",\n      \"caches_dir\": \"/Users/achyland/Library/Containers/com.yourteam.entitlement-jail/Data/Library/Containers/com.yourteam.entitlement-jail.ProbeService_net_client/Data/Library/Caches\",\n      \"desktop_dir\": \"/Users/achyland/Library/Containers/com.yourteam.entitlement-jail/Data/Library/Containers/com.yourteam.entitlement-jail.ProbeService_net_client/Data/Desktop\",\n      \"documents_dir\": \"/Users/achyland/Library/Containers/com.yourteam.entitlement-jail/Data/Library/Containers/com.yourteam.entitlement-jail.ProbeService_net_client/Data/Documents\",\n      \"downloads_dir\": \"/Users/achyland/Library/Containers/com.yourteam.entitlement-jail/Data/Library/Containers/com.yourteam.entitlement-jail.ProbeService_net_client/Data/Downloads\",\n      \"has_allow_dyld_env\": false,\n      \"has_allow_jit\": false,\n      \"has_allow_unsigned_exec_mem\": false,\n      \"has_app_sandbox\": true,\n      \"has_bookmarks_app_scope\": false,\n      \"has_disable_library_validation\": false,\n      \"has_downloads_rw\": false,\n      \"has_get_task_allow\": false,\n      \"has_network_client\": true,\n      \"has_user_selected_executable\": false,\n      \"has_user_selected_read_only\": false,\n      \"has_user_selected_read_write\": false,\n      \"home_dir\": \"/Users/achyland/Library/Containers/com.yourteam.entitlement-jail/Data/Library/Containers/com.yourteam.entitlement-jail.ProbeService_net_client/Data\",\n      \"prefs_path_guess\": \"/Users/achyland/Library/Containers/com.yourteam.entitlement-jail/Data/Library/Containers/com.yourteam.entitlement-jail.ProbeService_net_client/Data/Library/Preferences/com.yourteam.entitlement-jail.ProbeService_net_client.plist\",\n      \"tmp_dir\": \"/Users/achyland/Library/Containers/com.yourteam.entitlement-jail/Data/Library/Containers/com.yourteam.entitlement-jail.ProbeService_net_client/Data/tmp\"\n    },\n    \"capabilities_source\": \"static\",\n    \"service\": {\n      \"bundle_id\": \"com.yourteam.entitlement-jail.ProbeService_net_client\",\n      \"entitlements\": {\n        \"com.apple.security.app-sandbox\": true,\n        \"com.apple.security.network.client\": true\n      },\n      \"entitlements_error\": null,\n      \"kind\": \"probe\",\n      \"label\": \"net client\",\n      \"profile_id\": \"net_client\",\n      \"risk_reasons\": [],\n      \"risk_tier\": 0,\n      \"service_name\": \"ProbeService_net_client\",\n      \"tags\": [\n        \"network_client\",\n        \"probe\",\n        \"sandbox\"\n      ]\n    }\n  },\n  \"generated_at_unix_ms\": 1766618482913,\n  \"kind\": \"describe_service_report\",\n  \"result\": {\n    \"errno\": null,\n    \"error\": null,\n    \"exit_code\": 0,\n    \"normalized_outcome\": null,\n    \"ok\": true,\n    \"rc\": null,\n    \"stderr\": null,\n    \"stdout\": null\n  },\n  \"schema_version\": 1\n}\n",
      "stderr": ""
    }
  ]
}
